Data533_superman_Jade/Supermarket.db
Data533_superman_Jade/__init__.py
Data533_superman_Jade/main.py
Data533_superman_Jade/administer/__init__.py
Data533_superman_Jade/administer/account.py
Data533_superman_Jade/administer/inventory.py
Data533_superman_Jade/customer/__init__.py
Data533_superman_Jade/customer/members.py
Data533_superman_Jade/customer/transactions.py
Data533_superman_Jade-0.0.9.dist-info/METADATA
Data533_superman_Jade-0.0.9.dist-info/WHEEL
Data533_superman_Jade-0.0.9.dist-info/top_level.txt
Data533_superman_Jade-0.0.9.dist-info/RECORD
